<?xml version="1.0" encoding="UTF-8"?>
<vcs-root xmlns:xsi="http://www.w3.org/2001/XMLSchema-instance" uuid="06d3496a-b4ee-465f-b98e-3ca65768090f" type="jetbrains.git" xsi:noNamespaceSchemaLocation="http://www.jetbrains.com/teamcity/schemas/2018.1/project-config.xsd">
  <name>https://github.com/sashamerkulev/MapperJ</name>
  <param name="agentCleanFilesPolicy" value="ALL_UNTRACKED" />
  <param name="agentCleanPolicy" value="ON_BRANCH_CHANGE" />
  <param name="authMethod" value="PASSWORD" />
  <param name="branch" value="refs/heads/master" />
  <param name="ignoreKnownHosts" value="true" />
  <param name="push_url" value="https://github.com/sashamerkulev/MapperJ" />
  <param name="secure:password" value="credentialsJSON:cace62b5-4ee4-4e0e-be87-2e8c4214e54a" />
  <param name="submoduleCheckout" value="CHECKOUT" />
  <param name="teamcity:branchSpec" value="refs/heads/*" />
  <param name="url" value="https://github.com/sashamerkulev/MapperJ" />
  <param name="useAlternates" value="true" />
  <param name="username" value="sashamerkulev" />
  <param name="usernameStyle" value="USERID" />
</vcs-root>

